dynahost/__init__.py
dynahost/service.py
dynahost-1.1.0.data/data/etc/dynahost.service
dynahost-1.1.0.data/data/etc/dynahost_config_sample.ini
dynahost-1.1.0.dist-info/LICENSE.txt
dynahost-1.1.0.dist-info/METADATA
dynahost-1.1.0.dist-info/WHEEL
dynahost-1.1.0.dist-info/entry_points.txt
dynahost-1.1.0.dist-info/top_level.txt
dynahost-1.1.0.dist-info/RECORD
