Metadata-Version: 2.1
Name: dynahost
Version: 1.1.0
Summary: Web-service pour administrer des hôtes en adresse IP dynamique
Home-page: https://github.com/fkieber/dynahost
Author: Frédéric KIEBER
Author-email: contact@frkb.fr
License: MIT
Keywords: web-service dynhost dyndns ovh
Platform: UNKNOWN
Classifier: Development Status :: 5 - Production/Stable
Classifier: Environment :: Web Environment
Classifier: Intended Audience :: System Administrators
Classifier: License :: OSI Approved :: MIT License
Classifier: Natural Language :: French
Classifier: Operating System :: OS Independent
Classifier: Programming Language :: Python :: 3 :: Only
Classifier: Topic :: System
Classifier: Topic :: System :: Networking
Requires-Python: >=3
Requires-Dist: werkzeug
Requires-Dist: requests
Requires-Dist: html2text
Requires-Dist: bcrypt
